i11_ai/__init__.py
i11_ai-0.1.2.dist-info/METADATA
i11_ai-0.1.2.dist-info/WHEEL
i11_ai-0.1.2.dist-info/RECORD
