Metadata-Version: 2.1
Name: i11-ai
Version: 0.1.2
Summary: 
Author: Junaid Ali
Author-email: junaid.ali@inspire11.com
Requires-Python: >=3.11,<4.0
Classifier: Programming Language :: Python :: 3
Classifier: Programming Language :: Python :: 3.11
Classifier: Programming Language :: Python :: 3.12
